{
    "total": [
        {
            "id": "100065563803743",
            "count": 0
        },
        {
            "id": "61556970785395",
            "count": 0
        },
        {
            "id": "61552741752801",
            "count": 0
        },
        {
            "id": "100095178219503",
            "count": 0
        },
        {
            "id": "100080635460656",
            "count": 0
        },
        {
            "id": "100014003406050",
            "count": 0
        },
        {
            "id": "61559545041478",
            "count": 0
        },
        {
            "id": "100089281770842",
            "count": 0
        },
        {
            "id": "100083668701594",
            "count": 0
        },
        {
            "id": "61563450811249",
            "count": 0
        },
        {
            "id": "100086357945946",
            "count": 0
        },
        {
            "id": "100095044547095",
            "count": 0
        },
        {
            "id": "100085781785595",
            "count": 0
        },
        {
            "id": "61555031423113",
            "count": 0
        },
        {
            "id": "100079664662565",
            "count": 0
        },
        {
            "id": "100090372574797",
            "count": 0
        },
        {
            "id": "61553568390112",
            "count": 1
        },
        {
            "id": "100084384627485",
            "count": 0
        },
        {
            "id": "100053328709582",
            "count": 0
        }
    ],
    "week": [
        {
            "id": "100065563803743",
            "count": 0
        },
        {
            "id": "61556970785395",
            "count": 0
        },
        {
            "id": "61552741752801",
            "count": 0
        },
        {
            "id": "100095178219503",
            "count": 0
        },
        {
            "id": "100080635460656",
            "count": 0
        },
        {
            "id": "100014003406050",
            "count": 0
        },
        {
            "id": "61559545041478",
            "count": 0
        },
        {
            "id": "100089281770842",
            "count": 0
        },
        {
            "id": "100083668701594",
            "count": 0
        },
        {
            "id": "61563450811249",
            "count": 0
        },
        {
            "id": "100086357945946",
            "count": 0
        },
        {
            "id": "100095044547095",
            "count": 0
        },
        {
            "id": "100085781785595",
            "count": 0
        },
        {
            "id": "61555031423113",
            "count": 0
        },
        {
            "id": "100079664662565",
            "count": 0
        },
        {
            "id": "100090372574797",
            "count": 0
        },
        {
            "id": "61553568390112",
            "count": 1
        },
        {
            "id": "100084384627485",
            "count": 0
        },
        {
            "id": "100053328709582",
            "count": 0
        }
    ],
    "day": [
        {
            "id": "100065563803743",
            "count": 0
        },
        {
            "id": "61556970785395",
            "count": 0
        },
        {
            "id": "61552741752801",
            "count": 0
        },
        {
            "id": "100095178219503",
            "count": 0
        },
        {
            "id": "100080635460656",
            "count": 0
        },
        {
            "id": "100014003406050",
            "count": 0
        },
        {
            "id": "61559545041478",
            "count": 0
        },
        {
            "id": "100089281770842",
            "count": 0
        },
        {
            "id": "100083668701594",
            "count": 0
        },
        {
            "id": "61563450811249",
            "count": 0
        },
        {
            "id": "100086357945946",
            "count": 0
        },
        {
            "id": "100095044547095",
            "count": 0
        },
        {
            "id": "100085781785595",
            "count": 0
        },
        {
            "id": "61555031423113",
            "count": 0
        },
        {
            "id": "100079664662565",
            "count": 0
        },
        {
            "id": "100090372574797",
            "count": 0
        },
        {
            "id": "61553568390112",
            "count": 1
        },
        {
            "id": "100084384627485",
            "count": 0
        },
        {
            "id": "100053328709582",
            "count": 0
        }
    ],
    "time": 0,
    "last": {
        "time": 6,
        "day": [
            {
                "id": "100065563803743",
                "count": 0
            },
            {
                "id": "61556970785395",
                "count": 0
            },
            {
                "id": "61552741752801",
                "count": 0
            },
            {
                "id": "100095178219503",
                "count": 0
            },
            {
                "id": "100080635460656",
                "count": 0
            },
            {
                "id": "100014003406050",
                "count": 0
            },
            {
                "id": "61559545041478",
                "count": 0
            },
            {
                "id": "100089281770842",
                "count": 0
            },
            {
                "id": "100083668701594",
                "count": 0
            },
            {
                "id": "61563450811249",
                "count": 0
            },
            {
                "id": "100086357945946",
                "count": 0
            },
            {
                "id": "100095044547095",
                "count": 0
            },
            {
                "id": "100085781785595",
                "count": 0
            },
            {
                "id": "61555031423113",
                "count": 0
            },
            {
                "id": "100079664662565",
                "count": 0
            },
            {
                "id": "100090372574797",
                "count": 0
            },
            {
                "id": "61553568390112",
                "count": 0
            },
            {
                "id": "100084384627485",
                "count": 0
            },
            {
                "id": "100053328709582",
                "count": 0
            }
        ],
        "week": [
            {
                "id": "100065563803743",
                "count": 0
            },
            {
                "id": "61556970785395",
                "count": 0
            },
            {
                "id": "61552741752801",
                "count": 0
            },
            {
                "id": "100095178219503",
                "count": 0
            },
            {
                "id": "100080635460656",
                "count": 0
            },
            {
                "id": "100014003406050",
                "count": 0
            },
            {
                "id": "61559545041478",
                "count": 0
            },
            {
                "id": "100089281770842",
                "count": 0
            },
            {
                "id": "100083668701594",
                "count": 0
            },
            {
                "id": "61563450811249",
                "count": 0
            },
            {
                "id": "100086357945946",
                "count": 0
            },
            {
                "id": "100095044547095",
                "count": 0
            },
            {
                "id": "100085781785595",
                "count": 0
            },
            {
                "id": "61555031423113",
                "count": 0
            },
            {
                "id": "100079664662565",
                "count": 0
            },
            {
                "id": "100090372574797",
                "count": 0
            },
            {
                "id": "61553568390112",
                "count": 0
            },
            {
                "id": "100084384627485",
                "count": 0
            },
            {
                "id": "100053328709582",
                "count": 0
            }
        ]
    }
}